ckanext/__init__.py
ckanext/passwordless_api/__init__.py
ckanext/passwordless_api/__version__.py
ckanext/passwordless_api/logic.py
ckanext/passwordless_api/mailer.py
ckanext/passwordless_api/plugin.py
ckanext/passwordless_api/templates/reset_key.txt
ckanext/passwordless_api/templates/welcome_user.txt
ckanext/passwordless_api/util.py
ckanext_passwordless_api-1.1.11.dist-info/entry_points.txt
ckanext_passwordless_api-1.1.11.dist-info/WHEEL
ckanext_passwordless_api-1.1.11.dist-info/METADATA
ckanext_passwordless_api-1.1.11.dist-info/licenses/LICENSE
ckanext_passwordless_api-1.1.11.dist-info/RECORD
