Metadata-Version: 2.1
Name: ckanext-passwordless_api
Version: 1.1.11
Summary: Extension to allow paswordless login to the CKAN API
License: MIT
Keywords: CKAN,passwordless,token,auth
Author-email: Sam Woodcock <sam.woodcock@protonmail.com>
Requires-Python: >=3.8
Classifier: Programming Language :: Python
Classifier: Programming Language :: Python :: 3 :: Only
Classifier: Programming Language :: Python :: 3.10
Classifier: Programming Language :: Python :: 3.8
Classifier: Programming Language :: Python :: 3.9
Classifier: Topic :: Utilities
Requires-Dist: requests>=2.25.1
Project-URL: documentation, https://envidat.gitlab-pages.wsl.ch/ckanext-passwordless_api
Project-URL: homepage, https://gitlabext.wsl.ch/EnviDat/ckanext-passwordless_api.git
Project-URL: repository, https://gitlabext.wsl.ch/EnviDat/ckanext-passwordless_api.git
